[
  {
    "id": 0,
    "slug": "lunch-with-friends",
    "title": "대학교 친구들과 함께한 왁자지껄 점심시간",
    "date": "2024.03.26",
    "excerpt": "강의 사이 꿀맛 같은 점심시간! 친구들과 함께한 맛있는 시간과 소소한 수다들.",
    "category": "일상",
    "content": "오늘은 전공 강의가 끝나고 친구들과 다 같이 학교 근처 돈가스집에 갔다. \n\n시험 기간이 다가오고 있어서 그런지 다들 조금은 지친 기색이었지만, 음식이 나오자마자 금세 웃음꽃이 피었다. 학교생활 이야기부터 시작해서 최근 유행하는 취미들까지... 친구들과 나누는 수다는 언제나 즐겁다. \n\n맛있는 밥 한 끼와 친구들의 응원 덕분에 오후 강의도 힘을 내서 들을 수 있을 것 같다. 다음 주에는 근처 새로 생긴 텐동집에 가보기로 약속했다!"
  },
  {
    "id": -1,
    "slug": "soccer-match",
    "title": "운동장에서 쏟아낸 땀방울, 오늘의 축구 기록",
    "date": "2024.03.27",
    "excerpt": "오후 햇살 아래 운동장을 누비며 보낸 시간. 축구는 내 최고의 스트레스 해소제!",
    "category": "운동",
    "content": "오후 늦게 친구들과 운동장에 모였다. 따뜻한 햇살 아래 공을 차니 기분이 정말 상쾌했다. \n\n오늘은 미드필더로 뛰면서 경기 전체를 조율해보려 노력했다. 결정적인 패스 하나가 골로 연결되었을 때의 짜릿함! 90분 내내 운동장을 누비다 보니 숨은 가빴지만, 마음만큼은 아주 가벼워졌다. \n\n운동을 마치고 마시는 시원한 이온 음료의 맛은 그 어떤 것과도 비교할 수 없다. 역시 난 몸을 움직여야 살아있음을 느낀다."
  },
  {
    "id": -2,
    "slug": "gym-routine",
    "title": "저녁 헬스 오운완! 어제보다 더 강해진 나",
    "date": "2024.03.28",
    "excerpt": "무거운 바벨과 씨름하며 보낸 저녁. 매일 조금씩 성장하는 나를 발견하는 시간.",
    "category": "건강",
    "content": "오늘은 등 운동을 하는 날이다. 저녁을 먹고 소화시킨 후 곧장 헬스장으로 향했다. \n\n처음에는 데드리프트 무게가 버겁게 느껴졌지만, 집중력을 발휘해 목표했던 세트를 모두 마쳤다. 거울 속에 비친 땀 흐르는 내 모습을 보며 오늘도 해냈다는 성취감을 느낀다. \n\n매일 정직하게 노력한 만큼 몸이 변하는 것을 보는 것은 정말 매력적인 일이다. 샤워를 마치고 집으로 돌아가는 길, 밤공기가 유난히 시원하게 느껴진다. 내일은 스쿼트 기록에 도전해봐야겠다."
  },
  {
    "id": 1,
    "slug": "post-1",
    "title": "1번째 블로그 포스팅",
    "content": "오늘의 공부 내용입니다."
  },
  {
    "id": 2,
    "slug": "post-2",
    "title": "2번째 블로그 포스팅",
    "content": "오늘의 공부 내용입니다."
  },
  {
    "id": 3,
    "slug": "post-3",
    "title": "3번째 블로그 포스팅",
    "content": "오늘의 공부 내용입니다."
  },
  {
    "id": 4,
    "slug": "post-4",
    "title": "4번째 블로그 포스팅",
    "content": "오늘의 공부 내용입니다."
  },
  {
    "id": 5,
    "slug": "post-5",
    "title": "5번째 블로그 포스팅",
    "content": "오늘의 공부 내용입니다."
  },
  {
    "id": 6,
    "slug": "post-6",
    "title": "6번째 블로그 포스팅",
    "content": "오늘의 공부 내용입니다."
  },
  {
    "id": 7,
    "slug": "post-7",
    "title": "7번째 블로그 포스팅",
    "content": "오늘의 공부 내용입니다."
  },
  {
    "id": 8,
    "slug": "post-8",
    "title": "8번째 블로그 포스팅",
    "content": "오늘의 공부 내용입니다."
  },
  {
    "id": 9,
    "slug": "post-9",
    "title": "9번째 블로그 포스팅",
    "content": "오늘의 공부 내용입니다."
  },
  {
    "id": 10,
    "slug": "post-10",
    "title": "10번째 블로그 포스팅",
    "content": "오늘의 공부 내용입니다."
  },
  {
    "id": 11,
    "slug": "post-11",
    "title": "11번째 블로그 포스팅",
    "content": "오늘의 공부 내용입니다."
  },
  {
    "id": 12,
    "slug": "post-12",
    "title": "12번째 블로그 포스팅",
    "content": "오늘의 공부 내용입니다."
  },
  {
    "id": 13,
    "slug": "post-13",
    "title": "13번째 블로그 포스팅",
    "content": "오늘의 공부 내용입니다."
  },
  {
    "id": 14,
    "slug": "post-14",
    "title": "14번째 블로그 포스팅",
    "content": "오늘의 공부 내용입니다."
  },
  {
    "id": 15,
    "slug": "post-15",
    "title": "15번째 블로그 포스팅",
    "content": "오늘의 공부 내용입니다."
  },
  {
    "id": 16,
    "slug": "post-16",
    "title": "16번째 블로그 포스팅",
    "content": "오늘의 공부 내용입니다."
  },
  {
    "id": 17,
    "slug": "post-17",
    "title": "17번째 블로그 포스팅",
    "content": "오늘의 공부 내용입니다."
  },
  {
    "id": 18,
    "slug": "post-18",
    "title": "18번째 블로그 포스팅",
    "content": "오늘의 공부 내용입니다."
  },
  {
    "id": 19,
    "slug": "post-19",
    "title": "19번째 블로그 포스팅",
    "content": "오늘의 공부 내용입니다."
  },
  {
    "id": 20,
    "slug": "post-20",
    "title": "20번째 블로그 포스팅",
    "content": "오늘의 공부 내용입니다."
  },
  {
    "id": 21,
    "slug": "post-21",
    "title": "21번째 블로그 포스팅",
    "content": "오늘의 공부 내용입니다."
  },
  {
    "id": 22,
    "slug": "post-22",
    "title": "22번째 블로그 포스팅",
    "content": "오늘의 공부 내용입니다."
  },
  {
    "id": 23,
    "slug": "post-23",
    "title": "23번째 블로그 포스팅",
    "content": "오늘의 공부 내용입니다."
  },
  {
    "id": 24,
    "slug": "post-24",
    "title": "24번째 블로그 포스팅",
    "content": "오늘의 공부 내용입니다."
  },
  {
    "id": 25,
    "slug": "post-25",
    "title": "25번째 블로그 포스팅",
    "content": "오늘의 공부 내용입니다."
  },
  {
    "id": 26,
    "slug": "post-26",
    "title": "26번째 블로그 포스팅",
    "content": "오늘의 공부 내용입니다."
  },
  {
    "id": 27,
    "slug": "post-27",
    "title": "27번째 블로그 포스팅",
    "content": "오늘의 공부 내용입니다."
  },
  {
    "id": 28,
    "slug": "post-28",
    "title": "28번째 블로그 포스팅",
    "content": "오늘의 공부 내용입니다."
  },
  {
    "id": 29,
    "slug": "post-29",
    "title": "29번째 블로그 포스팅",
    "content": "오늘의 공부 내용입니다."
  },
  {
    "id": 30,
    "slug": "post-30",
    "title": "30번째 블로그 포스팅",
    "content": "오늘의 공부 내용입니다."
  },
  {
    "id": 31,
    "slug": "post-31",
    "title": "31번째 블로그 포스팅",
    "content": "오늘의 공부 내용입니다."
  },
  {
    "id": 32,
    "slug": "post-32",
    "title": "32번째 블로그 포스팅",
    "content": "오늘의 공부 내용입니다."
  },
  {
    "id": 33,
    "slug": "post-33",
    "title": "33번째 블로그 포스팅",
    "content": "오늘의 공부 내용입니다."
  },
  {
    "id": 34,
    "slug": "post-34",
    "title": "34번째 블로그 포스팅",
    "content": "오늘의 공부 내용입니다."
  },
  {
    "id": 35,
    "slug": "post-35",
    "title": "35번째 블로그 포스팅",
    "content": "오늘의 공부 내용입니다."
  },
  {
    "id": 36,
    "slug": "post-36",
    "title": "36번째 블로그 포스팅",
    "content": "오늘의 공부 내용입니다."
  },
  {
    "id": 37,
    "slug": "post-37",
    "title": "37번째 블로그 포스팅",
    "content": "오늘의 공부 내용입니다."
  },
  {
    "id": 38,
    "slug": "post-38",
    "title": "38번째 블로그 포스팅",
    "content": "오늘의 공부 내용입니다."
  },
  {
    "id": 39,
    "slug": "post-39",
    "title": "39번째 블로그 포스팅",
    "content": "오늘의 공부 내용입니다."
  },
  {
    "id": 40,
    "slug": "post-40",
    "title": "40번째 블로그 포스팅",
    "content": "오늘의 공부 내용입니다."
  },
  {
    "id": 41,
    "slug": "post-41",
    "title": "41번째 블로그 포스팅",
    "content": "오늘의 공부 내용입니다."
  },
  {
    "id": 42,
    "slug": "post-42",
    "title": "42번째 블로그 포스팅",
    "content": "오늘의 공부 내용입니다."
  },
  {
    "id": 43,
    "slug": "post-43",
    "title": "43번째 블로그 포스팅",
    "content": "오늘의 공부 내용입니다."
  },
  {
    "id": 44,
    "slug": "post-44",
    "title": "44번째 블로그 포스팅",
    "content": "오늘의 공부 내용입니다."
  },
  {
    "id": 45,
    "slug": "post-45",
    "title": "45번째 블로그 포스팅",
    "content": "오늘의 공부 내용입니다."
  },
  {
    "id": 46,
    "slug": "post-46",
    "title": "46번째 블로그 포스팅",
    "content": "오늘의 공부 내용입니다."
  },
  {
    "id": 47,
    "slug": "post-47",
    "title": "47번째 블로그 포스팅",
    "content": "오늘의 공부 내용입니다."
  },
  {
    "id": 48,
    "slug": "post-48",
    "title": "48번째 블로그 포스팅",
    "content": "오늘의 공부 내용입니다."
  },
  {
    "id": 49,
    "slug": "post-49",
    "title": "49번째 블로그 포스팅",
    "content": "오늘의 공부 내용입니다."
  },
  {
    "id": 50,
    "slug": "post-50",
    "title": "50번째 블로그 포스팅",
    "content": "오늘의 공부 내용입니다."
  }
]